<?xml version='1.0' encoding='windows-1252' ?>
<!DOCTYPE ViewObject SYSTEM "jbo_03_01.dtd">
<!---->

<ViewObject
   xmlns="http://xmlns.oracle.com/bc4j"
   Name="ContractTitleRoyaltyRateView"
   Version="11.1.1.59.23"
   OrderBy="EFFECTIVE_START_DATE,EFFECTIVE_END_DATE"
   BindingStyle="OracleName"
   CustomQuery="true"
   RowClass="com.pq.tracs.model.dao.ContractTitleRoyaltyRateViewRowImpl"
   ComponentClass="com.pq.tracs.model.dao.ContractTitleRoyaltyRateViewImpl"
   PageIterMode="Partial"
   UseGlueCode="false"
   FetchMode="FETCH_AS_NEEDED"
   FetchSize="15"
   RangeSize="10">
   <DesignTime>
      <Attr Name="_codeGenFlag2" Value="Access|Coll|VarAccess"/>
      <Attr Name="_isExpertMode" Value="true"/>
      <Attr Name="_objectSuperClassName"
         Value="com.pq.tracs.model.dao.TracsView"/>
      <Attr Name="_isCodegen" Value="true"/>
   </DesignTime>
   <SQLQuery><![CDATA[SELECT TitleRoyaltyRate.ID, 
       TitleRoyaltyRate.TITLE_ID, 
       TitleRoyaltyRate.ROYALTY_RATE_ID, 
       RoyaltyRate.MEDIA, 
       RoyaltyRate.RATE_TYPE, 
       RoyaltyRate.ROYALTY_RATE AS ROYALTY_RATE1, 
       RoyaltyRate.EFFECTIVE_START_DATE, 
       RoyaltyRate.EFFECTIVE_END_DATE, 
       RoyaltyRate.EXCEPTION_FLAG, 
       TitleRoyaltyRate.CREATED_BY, 
       TitleRoyaltyRate.CREATED_DATE, 
       TitleRoyaltyRate.LAST_UPDATED_BY, 
       TitleRoyaltyRate.LAST_UPDATED_DATE,
       RoyaltyRate.ID AS ID1
FROM TRAX_TITLE_ROYALTY_RATE TitleRoyaltyRate, TRAX_ROYALTY_RATE RoyaltyRate
WHERE TitleRoyaltyRate.ROYALTY_RATE_ID = RoyaltyRate.ID]]></SQLQuery>
   <EntityUsage
      Name="TitleRoyaltyRate"
      Entity="com.pq.tracs.model.bo.TitleRoyaltyRate" >
   </EntityUsage>
   <ViewAttribute
      Name="Id"
      EntityAttrName="Id"
      EntityUsage="TitleRoyaltyRate"
      AliasName="ID" >
   </ViewAttribute>
   <ViewAttribute
      Name="TitleId"
      EntityAttrName="TitleId"
      EntityUsage="TitleRoyaltyRate"
      AliasName="TITLE_ID" >
   </ViewAttribute>
   <ViewAttribute
      Name="RoyaltyRateId"
      EntityAttrName="RoyaltyRateId"
      EntityUsage="TitleRoyaltyRate"
      AliasName="ROYALTY_RATE_ID" >
   </ViewAttribute>
   <ViewAttribute
      Name="Media"
      IsPersistent="false"
      Precision="40"
      Type="java.lang.String"
      ColumnType="VARCHAR2"
      AliasName="MEDIA"
      Expression="MEDIA"
      SQLType="VARCHAR">
      <DesignTime>
         <Attr Name="_DisplaySize" Value="40"/>
      </DesignTime>
      <Properties>
         <SchemaBasedProperties>
            <LABEL
               ResId="com.pq.tracs.model.dao.ContractTitleRoyaltyRateView.Media_LABEL"/>
         </SchemaBasedProperties>
      </Properties>
   </ViewAttribute>
   <ViewAttribute
      Name="RateType"
      IsPersistent="false"
      Precision="40"
      Type="java.lang.String"
      ColumnType="VARCHAR2"
      AliasName="RATE_TYPE"
      Expression="RATE_TYPE"
      SQLType="VARCHAR">
      <DesignTime>
         <Attr Name="_DisplaySize" Value="40"/>
      </DesignTime>
      <Properties>
         <SchemaBasedProperties>
            <LABEL
               ResId="com.pq.tracs.model.dao.ContractTitleRoyaltyRateView.RateType_LABEL"/>
         </SchemaBasedProperties>
      </Properties>
   </ViewAttribute>
   <ViewAttribute
      Name="RoyaltyRate1"
      IsPersistent="false"
      Precision="10"
      Scale="3"
      Type="oracle.jbo.domain.Number"
      ColumnType="NUMBER"
      AliasName="ROYALTY_RATE1"
      Expression="ROYALTY_RATE1"
      SQLType="NUMERIC">
      <DesignTime>
         <Attr Name="_DisplaySize" Value="22"/>
      </DesignTime>
      <Properties>
         <SchemaBasedProperties>
            <LABEL
               ResId="com.pq.tracs.model.dao.ContractTitleRoyaltyRateView.RoyaltyRate1_LABEL"/>
         </SchemaBasedProperties>
      </Properties>
   </ViewAttribute>
   <ViewAttribute
      Name="EffectiveStartDate"
      IsPersistent="false"
      Type="oracle.jbo.domain.Date"
      ColumnType="DATE"
      AliasName="EFFECTIVE_START_DATE"
      Expression="EFFECTIVE_START_DATE"
      SQLType="DATE">
      <DesignTime>
         <Attr Name="_DisplaySize" Value="7"/>
      </DesignTime>
      <Properties>
         <SchemaBasedProperties>
            <LABEL
               ResId="com.pq.tracs.model.dao.ContractTitleRoyaltyRateView.EffectiveStartDate_LABEL"/>
         </SchemaBasedProperties>
      </Properties>
   </ViewAttribute>
   <ViewAttribute
      Name="EffectiveEndDate"
      IsPersistent="false"
      Type="oracle.jbo.domain.Date"
      ColumnType="DATE"
      AliasName="EFFECTIVE_END_DATE"
      Expression="EFFECTIVE_END_DATE"
      SQLType="DATE">
      <DesignTime>
         <Attr Name="_DisplaySize" Value="7"/>
      </DesignTime>
      <Properties>
         <SchemaBasedProperties>
            <LABEL
               ResId="com.pq.tracs.model.dao.ContractTitleRoyaltyRateView.EffectiveEndDate_LABEL"/>
         </SchemaBasedProperties>
      </Properties>
   </ViewAttribute>
   <ViewAttribute
      Name="ExceptionFlag"
      IsPersistent="false"
      Precision="1"
      Type="java.lang.String"
      ColumnType="CHAR"
      AliasName="EXCEPTION_FLAG"
      Expression="EXCEPTION_FLAG"
      SQLType="VARCHAR">
      <DesignTime>
         <Attr Name="_DisplaySize" Value="1"/>
      </DesignTime>
      <Properties>
         <SchemaBasedProperties>
            <LABEL
               ResId="com.pq.tracs.model.dao.ContractTitleRoyaltyRateView.ExceptionFlag_LABEL"/>
         </SchemaBasedProperties>
      </Properties>
   </ViewAttribute>
   <ViewAttribute
      Name="CreatedBy"
      IsUpdateable="false"
      EntityAttrName="CreatedBy"
      EntityUsage="TitleRoyaltyRate"
      AliasName="CREATED_BY" >
      <Properties>
         <SchemaBasedProperties>
            <LABEL
               ResId="com.pq.tracs.model.dao.ContractTitleRoyaltyRateView.CreatedBy_LABEL"/>
         </SchemaBasedProperties>
      </Properties>
   </ViewAttribute>
   <ViewAttribute
      Name="CreatedDate"
      IsUpdateable="false"
      EntityAttrName="CreatedDate"
      EntityUsage="TitleRoyaltyRate"
      AliasName="CREATED_DATE" >
      <Properties>
         <SchemaBasedProperties>
            <LABEL
               ResId="com.pq.tracs.model.dao.ContractTitleRoyaltyRateView.CreatedDate_LABEL"/>
            <FMT_FORMATTER
               ResId="com.pq.tracs.model.dao.ContractTitleRoyaltyRateView.CreatedDate_FMT_FORMATTER"/>
         </SchemaBasedProperties>
      </Properties>
   </ViewAttribute>
   <ViewAttribute
      Name="LastUpdatedBy"
      EntityAttrName="LastUpdatedBy"
      EntityUsage="TitleRoyaltyRate"
      AliasName="LAST_UPDATED_BY" >
      <Properties>
         <SchemaBasedProperties>
            <LABEL
               ResId="com.pq.tracs.model.dao.ContractTitleRoyaltyRateView.LastUpdatedBy_LABEL"/>
         </SchemaBasedProperties>
      </Properties>
   </ViewAttribute>
   <ViewAttribute
      Name="LastUpdatedDate"
      IsUpdateable="false"
      EntityAttrName="LastUpdatedDate"
      EntityUsage="TitleRoyaltyRate"
      AliasName="LAST_UPDATED_DATE" >
      <Properties>
         <SchemaBasedProperties>
            <LABEL
               ResId="com.pq.tracs.model.dao.ContractTitleRoyaltyRateView.LastUpdatedDate_LABEL"/>
            <FMT_FORMATTER
               ResId="com.pq.tracs.model.dao.ContractTitleRoyaltyRateView.LastUpdatedDate_FMT_FORMATTER"/>
            <FMT_FORMAT
               ResId="com.pq.tracs.model.dao.ContractTitleRoyaltyRateView.LastUpdatedDate_FMT_FORMAT"/>
         </SchemaBasedProperties>
      </Properties>
   </ViewAttribute>
   <ViewAttribute
      Name="Id1"
      IsPersistent="false"
      IsNotNull="true"
      Precision="38"
      Scale="0"
      Type="oracle.jbo.domain.Number"
      ColumnType="NUMBER"
      AliasName="ID1"
      Expression="ID1"
      SQLType="NUMERIC" >
      <DesignTime>
         <Attr Name="_DisplaySize" Value="22" />
      </DesignTime>
   </ViewAttribute>
   <ViewCriteria
      Name="ContractTitleRoyaltyRateViewCriteria"
      ViewObjectName="com.pq.tracs.model.dao.ContractTitleRoyaltyRateView"
      Conjunction="AND">
      <Properties>
         <CustomProperties>
            <Property
               Name="displayOperators"
               Value="InAdvancedMode"/>
            <Property
               Name="autoExecute"
               Value="false"/>
            <Property
               Name="allowConjunctionOverride"
               Value="true"/>
            <Property
               Name="showInList"
               Value="true"/>
            <Property
               Name="mode"
               Value="Basic"/>
         </CustomProperties>
      </Properties>
      <ViewCriteriaRow
         Name="vcrow30"
         UpperColumns="1">
         <ViewCriteriaItem
            Name="ContractTitleRoyaltyRateViewCriteria_vcrow30_Media"
            ViewAttribute="Media"
            Operator="STARTSWITH"
            Conjunction="AND"
            Required="Optional"/>
         <ViewCriteriaItem
            Name="ContractTitleRoyaltyRateViewCriteria_vcrow30_RateType"
            ViewAttribute="RateType"
            Operator="STARTSWITH"
            Conjunction="AND"
            Required="Optional"/>
         <ViewCriteriaItem
            Name="ContractTitleRoyaltyRateViewCriteria_vcrow30_RoyaltyRate1"
            ViewAttribute="RoyaltyRate1"
            Operator="="
            Conjunction="AND"
            Required="Optional"/>
         <ViewCriteriaItem
            Name="ContractTitleRoyaltyRateViewCriteria_vcrow30_EffectiveStartDate"
            ViewAttribute="EffectiveStartDate"
            Operator="="
            Conjunction="AND"
            Required="Optional"/>
         <ViewCriteriaItem
            Name="ContractTitleRoyaltyRateViewCriteria_vcrow30_EffectiveEndDate"
            ViewAttribute="EffectiveEndDate"
            Operator="="
            Conjunction="AND"
            Required="Optional"/>
         <ViewCriteriaItem
            Name="ContractTitleRoyaltyRateViewCriteria_vcrow30_ExceptionFlag"
            ViewAttribute="ExceptionFlag"
            Operator="STARTSWITH"
            Conjunction="AND"
            Required="Optional"/>
         <ViewCriteriaItem
            Name="ContractTitleRoyaltyRateViewCriteria_vcrow30_CreatedBy"
            ViewAttribute="CreatedBy"
            Operator="STARTSWITH"
            Conjunction="AND"
            Required="Optional"/>
         <ViewCriteriaItem
            Name="ContractTitleRoyaltyRateViewCriteria_vcrow30_CreatedDate"
            ViewAttribute="CreatedDate"
            Operator="="
            Conjunction="AND"
            Required="Optional"/>
         <ViewCriteriaItem
            Name="ContractTitleRoyaltyRateViewCriteria_vcrow30_LastUpdatedBy"
            ViewAttribute="LastUpdatedBy"
            Operator="STARTSWITH"
            Conjunction="AND"
            Required="Optional"/>
         <ViewCriteriaItem
            Name="ContractTitleRoyaltyRateViewCriteria_vcrow30_LastUpdatedDate"
            ViewAttribute="LastUpdatedDate"
            Operator="="
            Conjunction="AND"
            Required="Optional"/>
      </ViewCriteriaRow>
   </ViewCriteria>
   <ResourceBundle>
      <PropertiesBundle
         PropertiesFile="com.pq.tracs.model.ModelBundle"/>
   </ResourceBundle>
</ViewObject>
